mmpy_packagefiles/__init__.py
mmpy_packagefiles/database.py
mmpy_packagefiles/obvious.py
mmpy_packagefiles/parse.py
mmpy_packagefiles/proof.py
mmpy_packagefiles/scratch.py
mmpy_packagefiles/theory.py
mmpy_packagefiles/training_data.py
mmpy_packagefiles-0.0.10.dist-info/LICENSE
mmpy_packagefiles-0.0.10.dist-info/METADATA
mmpy_packagefiles-0.0.10.dist-info/WHEEL
mmpy_packagefiles-0.0.10.dist-info/top_level.txt
mmpy_packagefiles-0.0.10.dist-info/RECORD
